UnderArmour/UnderArmour.py
UnderArmour/__init__.py
UnderArmour-0.1.2.dist-info/DESCRIPTION.rst
UnderArmour-0.1.2.dist-info/METADATA
UnderArmour-0.1.2.dist-info/RECORD
UnderArmour-0.1.2.dist-info/WHEEL
UnderArmour-0.1.2.dist-info/metadata.json
UnderArmour-0.1.2.dist-info/top_level.txt
