Metadata-Version: 2.0
Name: UnderArmour
Version: 0.1.2
Summary: Python SDK for Under Armour API
Home-page: https://github.com/igorfala/python-under-armour
Author: Igor Fala
Author-email: ifala88@gmail.com
License: MIT
Keywords: API OAUTH UnderArmour
Platform: UNKNOWN
Classifier: Development Status :: 3 - Alpha
Classifier: Intended Audience :: Developers
Classifier: Programming Language :: Python :: Implementation :: PyPy
Classifier: License :: OSI Approved :: MIT License
Classifier: Programming Language :: Python :: 2
Classifier: Programming Language :: Python :: 2.6
Classifier: Programming Language :: Python :: 2.7
Classifier: Programming Language :: Python :: 3
Classifier: Programming Language :: Python :: 3.3
Classifier: Programming Language :: Python :: 3.4
Classifier: Programming Language :: Python :: 3.5
Requires-Dist: oauthlib (==2.0.0)
Requires-Dist: requests (==2.12.1)
Requires-Dist: requests-oauthlib (==0.7.0)
